Metadata-Version: 2.4
Name: yamu
Version: 0.1.0
Summary: game library manager
Requires-Python: >=3.10
Requires-Dist: PyYAML>=6.0
Requires-Dist: Jinja2>=3.1
Provides-Extra: dev
Requires-Dist: pytest>=7.4; extra == "dev"
Requires-Dist: ruff>=0.6.0; extra == "dev"
Provides-Extra: docs
Requires-Dist: sphinx>=7.2; extra == "docs"
Requires-Dist: pydata-sphinx-theme>=0.15; extra == "docs"
Requires-Dist: sphinx-copybutton>=0.5; extra == "docs"
Requires-Dist: sphinx-design>=0.5; extra == "docs"
